{
    "child": {
        "child1": {
            "child1": {
                "directory": "",
                "height": 834,
                "profile": "2b7c4080-0ddd-46c5-8f23-563fd3ba789d",
                "readOnly": false,
                "synchronizedInput": false,
                "type": "Terminal",
                "uuid": "c2dd8fac-087a-4bef-84d3-976b8edfadb9",
                "width": 1540
            },
            "child2": {
                "directory": "",
                "height": 833,
                "profile": "2b7c4080-0ddd-46c5-8f23-563fd3ba789d",
                "readOnly": false,
                "synchronizedInput": false,
                "type": "Terminal",
                "uuid": "1afaf060-dcc4-4f30-8710-219ee4f7c7ae",
                "width": 1540
            },
            "orientation": 1,
            "position": 50,
            "ratio": 0.5,
            "type": "Paned"
        },
        "child2": {
            "child1": {
                "directory": "",
                "height": 834,
                "profile": "2b7c4080-0ddd-46c5-8f23-563fd3ba789d",
                "readOnly": false,
                "synchronizedInput": false,
                "type": "Terminal",
                "uuid": "5f92830b-cca2-4802-903c-d5dfdefc2db1",
                "width": 1541
            },
            "child2": {
                "directory": "",
                "height": 833,
                "profile": "2b7c4080-0ddd-46c5-8f23-563fd3ba789d",
                "readOnly": false,
                "synchronizedInput": false,
                "type": "Terminal",
                "uuid": "aa76b008-621f-474a-95b8-6747e28cc566",
                "width": 1541
            },
            "orientation": 1,
            "position": 50,
            "ratio": 0.5,
            "type": "Paned"
        },
        "orientation": 0,
        "position": 49,
        "ratio": 0.499675535366645052,
        "type": "Paned"
    },
    "height": 1668,
    "name": "${title}",
    "synchronizedInput": true,
    "type": "Session",
    "uuid": "d2f75b94-0948-49dd-ad1d-016394c7953a",
    "version": "1.0",
    "width": 3082
}